GalCubeCraft/__init__.py
GalCubeCraft/core.py
GalCubeCraft/gui.py
GalCubeCraft/test.py
GalCubeCraft/utils.py
GalCubeCraft/visualise.py
galcubecraft-1.0.1.dist-info/licenses/LICENSE
galcubecraft-1.0.1.dist-info/METADATA
galcubecraft-1.0.1.dist-info/WHEEL
galcubecraft-1.0.1.dist-info/top_level.txt
galcubecraft-1.0.1.dist-info/RECORD
