Metadata-Version: 2.4
Name: GalCubeCraft
Version: 1.0.1
Summary: A synthetic IFU spectral cube generator with a theoretical rotating galaxy disk model
Author-email: Arnab Lahiry <arnablahiry08@gmail.com>
Project-URL: Homepage, https://github.com/arnablahiry/gal-cube-craft
Requires-Python: >=3.8
License-File: LICENSE
Requires-Dist: numpy
Requires-Dist: scipy
Requires-Dist: torch
Requires-Dist: astropy
Requires-Dist: matplotlib
Requires-Dist: scikit-learn
Requires-Dist: astrodendro
Requires-Dist: pytest
Dynamic: license-file
